setup.cfg
setup.py
zerocater/__init__.py
zerocater/client.py
zerocater.egg-info/PKG-INFO
zerocater.egg-info/SOURCES.txt
zerocater.egg-info/dependency_links.txt
zerocater.egg-info/pbr.json
zerocater.egg-info/top_level.txt