Metadata-Version: 1.1
Name: zerocater
Version: 0.0.1
Summary: Python interface to ZeroCater
Home-page: https://github.com/ZeroCater/PyZeroCater
Author: ZeroCater
Author-email: tech@zerocater.com
License: MIT
Download-URL: https://github.com/ZeroCater/PyZeroCater/tarball/0.0.1
Keywords: zerocater food delivery meal planning catering lunch
Platform: UNKNOWN
Classifier: License :: OSI Approved :: MIT License
Classifier: Programming Language :: Python
Classifier: Development Status :: 5 - Production/Stable
Classifier: Intended Audience :: Developers
Classifier: Topic :: Internet :: WWW/HTTP
